.coveragerc
.editorconfig
.readthedocs.yml
.travis.yml
CHANGES.rst
CONTRIBUTORS.rst
DEVELOP.rst
LICENSE.GPL
LICENSE.rst
MANIFEST.in
README.rst
base.cfg
bobtemplate.cfg
buildout.cfg
constraints.txt
constraints_plone43.txt
constraints_plone50.txt
constraints_plone51.txt
constraints_plone52.txt
make.bat
requirements.txt
setup.cfg
setup.py
test_plone43.cfg
test_plone50.cfg
test_plone51.cfg
test_plone52.cfg
tox.ini
source/conf.py
source/index.rst
source/images/behavior.png
source/images/contentrules.png
source/images/folder-edit.png
source/images/folder-sync.png
source/images/out.html
source/images/placeholder.txt
source/images/syncsettings.png
src/collective/__init__.py
src/collective.contentsync2.egg-info/PKG-INFO
src/collective.contentsync2.egg-info/SOURCES.txt
src/collective.contentsync2.egg-info/dependency_links.txt
src/collective.contentsync2.egg-info/entry_points.txt
src/collective.contentsync2.egg-info/namespace_packages.txt
src/collective.contentsync2.egg-info/not-zip-safe
src/collective.contentsync2.egg-info/requires.txt
src/collective.contentsync2.egg-info/top_level.txt
src/collective/contentsync/__init__.py
src/collective/contentsync/configure.zcml
src/collective/contentsync/interfaces.py
src/collective/contentsync/logger.py
src/collective/contentsync/permissions.zcml
src/collective/contentsync/setuphandlers.py
src/collective/contentsync/testing.py
src/collective/contentsync/browser/__init__.py
src/collective/contentsync/browser/configure.zcml
src/collective/contentsync/browser/overrides/.gitkeep
src/collective/contentsync/browser/static/.gitkeep
src/collective/contentsync/locales/README.rst
src/collective/contentsync/locales/__init__.py
src/collective/contentsync/locales/collective.contentsync.pot
src/collective/contentsync/locales/update.py
src/collective/contentsync/locales/update.sh
src/collective/contentsync/locales/en/LC_MESSAGES/collective.contentsync.po
src/collective/contentsync/profiles/default/browserlayer.xml
src/collective/contentsync/profiles/default/catalog.xml
src/collective/contentsync/profiles/default/contentrules.xml
src/collective/contentsync/profiles/default/controlpanel.xml
src/collective/contentsync/profiles/default/metadata.xml
src/collective/contentsync/profiles/default/rolemap.xml
src/collective/contentsync/profiles/default/registry/main.xml
src/collective/contentsync/profiles/default/registry/sync.xml
