Metadata-Version: 2.1
Name: collective.contentsync2
Version: 1.0b3
Summary: Content sync between Plone sites
Home-page: https://github.com/collective/collective.contentsync
Author: Thomas Massmann, Andreas Jung
Author-email: info@zopyx.com
License: GPL version 2
Project-URL: PyPI, https://pypi.python.org/pypi/collective.contentsync2
Project-URL: Source, https://github.com/collective/collective.contentsync2
Project-URL: Tracker, https://github.com/collective/collective.contentsync2/issues
Project-URL: Documentation, https://collective.contentsync2.readthedocs.io/en/latest/
Keywords: Python Plone CMS
Platform: UNKNOWN
Classifier: Environment :: Web Environment
Classifier: Framework :: Plone
Classifier: Framework :: Plone :: Addon
Classifier: Framework :: Plone :: 5.2
Classifier: Programming Language :: Python
Classifier: Programming Language :: Python :: 3.7
Classifier: Programming Language :: Python :: 3.8
Classifier: Operating System :: OS Independent
Classifier: License :: OSI Approved :: GNU General Public License v2 (GPLv2)
Requires-Python: >=3.7
Provides-Extra: test
